{
  "config" : {
    "adcolony" : {
      "adcolony_app_id" : "",
      "adcolony_interstitial_id" : "",
      "adcolony_rewarded_id" : ""
    },
    "admob" : {
      "admob_banner_id" : "ca-app-pub-8652080185669862/4554869599",
      "admob_interstitial_id" : "ca-app-pub-8652080185669862/6584274748",
      "admob_native_id" : "ca-app-pub-8652080185669862/3958111407",
      "admob_rewarded_id" : "",
      "admob_unit_id" : ""
    },
    "appodeal" : {
      "appodeal_app_key" : ""
    },
    "facebook" : {
      "facebook_banner_id" : "109352197869530_110046881133395",
      "facebook_interstitial_id" : "109352197869530_110047051133378",
      "facebook_native_id" : "109352197869530_110047184466698"
    },
    "mode_ads_banner" : "facebook",
    "mode_ads_interstitial" : "facebook",
    "mode_ads_native_enabled" : true,
    "mode_ads_rewarded" : "0",
    "mode_button_ads_action" : "https://play.google.com/store/apps/details?id=com.GuideforTentacleocker.locker",
    "unity" : {
      "unity_app_id" : "",
      "unity_banner_id" : "",
      "unity_interstitial_id" : "",
      "unity_rewarded_id" : ""
    },
    "update" : {
      "enable_update_closed" : true,
      "update_action" : "",
      "update_msg" : "update your app for grt all favorite now",
      "update_state" : false,
      "update_title" : "update your app"
    },
    "app" : {
      "mode_off_version" : "0"
    }
  },
  "posts" : [
    {
      "id" : 0,
      "imageURL" : "https://dadamou.github.io/Gartic-phone/n1.png",
      "state" : "free",
      "title" : "",
      "description" : "",
      "written" : "<p>Gartic Phone , popularized by Kameto on Twitch in recent days, is the succession of Skribble.io and Garlic.io.&nbsp;</p><p>Developed by Onrizon Social Games, the creators of Garlic.io, this party-game allows you to play with friends from 4 players and up to 30, all on a web browser.&nbsp;</p><p>You can therefore play this game on your PC or on your iOS or Android smartphone , the principle of which is the same as that of the Arabic telephone.&nbsp;</p><p>We explain in this article how to play this new party-game sensation, and you can find this trick in our Gartic Phone guide .</p>"
    },
    {
      "id" : 1,
      "imageURL" : "https://dadamou.github.io/Gartic-phone/n2.png",
      "state" : "free",
      "title" : "",
      "description" : "",
      "written" : "<p>HOW TO PLAY GARTIC PHONE?<p><p>The principle of the game is the same as that of the Arabic telephone: the first player proposes a sentence, then the second player must draw to try to make the next player guess this sentence.&nbsp;</p><p>Then the fourth player has to draw again to guess the sentence that the third player understood, and so on.&nbsp;</p><p>At the end of the game, the players compare the last guessed sentence to the starting sentence, which should be as close as possible.&nbsp;</p><p>In fact, the more players there are, the less similar the sentences will be!</p>"
    },
    {
      "id" : 2,
      "imageURL" : "https://dadamou.github.io/Gartic-phone/n3.png",
      "state" : "free",
      "title" : "",
      "description" : "",
      "written" : "<p>PLAY GARTIC PHONE<p><p>1. Launch the official Gartic Phone website</p><p>2. Choose your username</p><p>3. Then set your living room: choose the game mode ( free game or kick-off ), the duration, the maximum number of laps...</p>"
    },
    {
      "id" : 3,
      "imageURL" : "https://dadamou.github.io/Gartic-phone/n4.png",
      "state" : "free",
      "title" : "",
      "description" : "",
      "written" : "<p>Free play mode is the default mode, while easy play mode allows you to take your time since the timer won&apos;t start until the majority of players have finished drawing.</p>"
    },
    {
      "id" : 4,
      "imageURL" : "https://dadamou.github.io/Gartic-phone/n5.png",
      "state" : "free",
      "title" : "",
      "description" : "",
      "written" : "<p>If you don&apos;t have enough players to start a game, you can count on the game&apos;s official Discord , being careful to choose the French language when joining the server.</p>"
    },
    {
      "id" : 5,
      "imageURL" : "https://dadamou.github.io/Gartic-phone/n7.png",
      "state" : "free",
      "title" : "",
      "description" : "",
      "written" : ""
    },
       {
      "id" : 6,
      "imageURL" : "https://dadamou.github.io/Gartic-phone/n14.png",
      "state" : "free",
      "title" : "",
      "description" : "",
      "written" : ""
    },
    {
      "id" : 7,
      "imageURL" : "https://dadamou.github.io/Gartic-phone/n8.png",
      "state" : "free",
      "title" : "",
      "description" : "",
      "written" : ""
   },
    {
      "id" : 8,
      "imageURL" : "https://dadamou.github.io/Gartic-phone/n9.png",
      "state" : "free",
      "title" : "",
      "description" : "",
      "written" : ""
    },
    {
      "id" : 8,
      "imageURL" : "https://dadamou.github.io/Gartic-phone/n10.png",
      "state" : "free",
      "title" : "",
      "description" : "",
      "written" : ""
    },
    {
      "id" : 10,
      "imageURL" : "https://dadamou.github.io/Gartic-phone/n11.png",
      "state" : "free",
      "title" : "",
      "description" : "",
      "written" : ""
    },
    {
      "id" : 11,
      "imageURL" : "https://dadamou.github.io/Gartic-phone/n12.png",
      "state" : "free",
      "title" : "",
      "description" : "",
      "written" : ""
    },
    {
      "id" : 12,
      "imageURL" : "https://dadamou.github.io/Gartic-phone/n13.png",
      "state" : "free",
      "title" : "",
      "description" : "",
      "written" : ""
    },
    {
      "id" : 13,
      "imageURL" : "https://dadamou.github.io/Gartic-phone/n14.png",
      "state" : "free",
      "title" : "",
      "description" : "",
      "written" : ""
    }
  ]
}
